ghcopilot/__init__.py
ghcopilot/api.py
ghcopilot/cli.py
ghcopilot-0.1.0.dist-info/LICENSE
ghcopilot-0.1.0.dist-info/METADATA
ghcopilot-0.1.0.dist-info/WHEEL
ghcopilot-0.1.0.dist-info/entry_points.txt
ghcopilot-0.1.0.dist-info/top_level.txt
ghcopilot-0.1.0.dist-info/RECORD
